{
    "names": {
        "en": "Baxcalibur"
    },
    "national_id": 998,
    "types": [
        "Dragon",
        "Ice"
    ],
    "gender_ratios": {
        "male": 50.0,
        "female": 50.0
    },
    "catch_rate": 10,
    "height_eu": "2.1\u00a0m",
    "weight_eu": "210.0\u00a0kg",
    "leveling_rate": "Slow",
    "ev_yield": {
        "hp": 0,
        "atk": 3,
        "def": 0,
        "sp_atk": 0,
        "sp_def": 0,
        "speed": 0
    },
    "base_friendship": 50,
    "base_stats": {
        "hp": 115,
        "atk": 145,
        "def": 92,
        "sp_atk": 75,
        "sp_def": 86,
        "speed": 87
    },
    "evolution_from": "Arctibax",
    "categories": {
        "en": "Ice Dragon Pok\u00e9mon"
    },
    "evolutions": [],
    "pokedex_entries": {
        "Ruby": {
            "en": "This Pok\u00e9mon blasts cryogenic air out from its mouth. This air can instantly freeze even liquid-hot lava."
        }
    },
    "move_learnsets": [
        {
            "games": [
                "Sun",
                "Moon"
            ],
            "learnset": [],
            "learnsets": [
                {
                    "move": "Tackle",
                    "level": 1
                },
                {
                    "move": "Icy Wind",
                    "level": 6
                },
                {
                    "move": "Dragon Breath",
                    "level": 12
                },
                {
                    "move": "Focus Energy",
                    "level": 18
                },
                {
                    "move": "Bite",
                    "level": 24
                },
                {
                    "move": "Ice Fang",
                    "level": 29
                },
                {
                    "move": "Dragon Claw",
                    "level": 35
                },
                {
                    "move": "Take Down",
                    "level": 42
                },
                {
                    "move": "Ice Beam",
                    "level": 48
                },
                {
                    "move": "Crunch",
                    "level": 55
                },
                {
                    "move": "Icicle Crash",
                    "level": 62
                },
                {
                    "move": "Take Down",
                    "tm": "TM1"
                },
                {
                    "move": "Scary Face",
                    "tm": "TM6"
                },
                {
                    "move": "Protect",
                    "tm": "TM7"
                },
                {
                    "move": "Thunder Fang",
                    "tm": "TM9"
                },
                {
                    "move": "Ice Fang",
                    "tm": "TM10"
                },
                {
                    "move": "Facade",
                    "tm": "TM25"
                },
                {
                    "move": "Aerial Ace",
                    "tm": "TM27"
                },
                {
                    "move": "Bulldoze",
                    "tm": "TM28"
                },
                {
                    "move": "Icy Wind",
                    "tm": "TM34"
                },
                {
                    "move": "Dragon Tail",
                    "tm": "TM44"
                },
                {
                    "move": "Avalanche",
                    "tm": "TM46"
                },
                {
                    "move": "Endure",
                    "tm": "TM47"
                },
                {
                    "move": "Rain Dance",
                    "tm": "TM50"
                },
                {
                    "move": "Snowscape",
                    "tm": "TM52"
                },
                {
                    "move": "Dig",
                    "tm": "TM55"
                },
                {
                    "move": "False Swipe",
                    "tm": "TM57"
                },
                {
                    "move": "Brick Break",
                    "tm": "TM58"
                },
                {
                    "move": "Zen Headbutt",
                    "tm": "TM59"
                },
                {
                    "move": "Body Slam",
                    "tm": "TM66"
                },
                {
                    "move": "Sleep Talk",
                    "tm": "TM70"
                },
                {
                    "move": "Dragon Claw",
                    "tm": "TM78"
                },
                {
                    "move": "Stomping Tantrum",
                    "tm": "TM84"
                },
                {
                    "move": "Rest",
                    "tm": "TM85"
                },
                {
                    "move": "Swords Dance",
                    "tm": "TM88"
                },
                {
                    "move": "Body Press",
                    "tm": "TM89"
                },
                {
                    "move": "Iron Head",
                    "tm": "TM99"
                },
                {
                    "move": "Dragon Dance",
                    "tm": "TM100"
                },
                {
                    "move": "Substitute",
                    "tm": "TM103"
                },
                {
                    "move": "Crunch",
                    "tm": "TM108"
                },
                {
                    "move": "Dragon Pulse",
                    "tm": "TM115"
                },
                {
                    "move": "Helping Hand",
                    "tm": "TM130"
                },
                {
                    "move": "Ice Beam",
                    "tm": "TM135"
                },
                {
                    "move": "Blizzard",
                    "tm": "TM143"
                },
                {
                    "move": "Earthquake",
                    "tm": "TM149"
                },
                {
                    "move": "Giga Impact",
                    "tm": "TM152"
                },
                {
                    "move": "Outrage",
                    "tm": "TM156"
                },
                {
                    "move": "Hyper Beam",
                    "tm": "TM163"
                },
                {
                    "move": "Draco Meteor",
                    "tm": "TM169"
                },
                {
                    "move": "Tera Blast",
                    "tm": "TM171"
                }
            ]
        }
    ]
}